app_use/__init__.py
app_use/cli.py
app_use/utils.py
app_use/agent/__init__.py
app_use/agent/gif.py
app_use/agent/prompts.py
app_use/agent/service.py
app_use/agent/system_prompt.md
app_use/agent/views.py
app_use/agent/memory/__init__.py
app_use/agent/memory/service.py
app_use/agent/memory/views.py
app_use/agent/message_manager/__init__.py
app_use/agent/message_manager/service.py
app_use/agent/message_manager/utils.py
app_use/agent/message_manager/views.py
app_use/app/app.py
app_use/app/gestures.py
app_use/cli/__init__.py
app_use/cli/appium.py
app_use/cli/cli.py
app_use/cli/config.py
app_use/cli/devices.py
app_use/cli/doctor.py
app_use/cli/gui.py
app_use/cli/setup.py
app_use/cli/start.py
app_use/cli/utils.py
app_use/controller/service.py
app_use/controller/views.py
app_use/controller/registry/service.py
app_use/nodes/app_node.py
app_use/nodes/appium_tree_builder.py
app_use/nodes/history_tree_processor/__init__.py
app_use/nodes/history_tree_processor/service.py
app_use/nodes/history_tree_processor/view.py
app_use-0.0.3.dist-info/METADATA
app_use-0.0.3.dist-info/WHEEL
app_use-0.0.3.dist-info/entry_points.txt
app_use-0.0.3.dist-info/licenses/LICENSE
app_use-0.0.3.dist-info/RECORD
