Metadata-Version: 2.4
Name: app-use
Version: 0.0.3
Summary: Make mobile apps accessible for AI agents
Project-URL: Repository, https://github.com/erickjtorres/app-use
Project-URL: Homepage, https://github.com/erickjtorres/app-use
Project-URL: Bug Tracker, https://github.com/erickjtorres/app-use/issues
Project-URL: Documentation, https://github.com/erickjtorres/app-use#readme
Author: Erick Torres-Moreno
License-File: LICENSE
Keywords: agent,ai,android,app-use,appium,automation,browser-use,ios,mobile,mobile-use,ui-automation
Classifier: License :: OSI Approved :: MIT License
Classifier: Operating System :: OS Independent
Classifier: Programming Language :: Python :: 3
Requires-Python: <4.0,>=3.11
Requires-Dist: appium-python-client>=5.1.1
Requires-Dist: faiss-cpu>=1.11.0
Requires-Dist: google-api-core>=2.25.0
Requires-Dist: google-generativeai>=0.8.5
Requires-Dist: langchain-anthropic==0.3.14
Requires-Dist: langchain-aws>=0.2.24
Requires-Dist: langchain-core==0.3.63
Requires-Dist: langchain-deepseek>=0.1.3
Requires-Dist: langchain-google-genai<2.1.5
Requires-Dist: langchain-ollama==0.3.3
Requires-Dist: langchain-openai==0.3.19
Requires-Dist: langchain>=0.3.25
Requires-Dist: mem0ai>=0.1.104
Requires-Dist: openai>=1.0.0
Requires-Dist: opencv-python>=4.11.0
Requires-Dist: pillow>=11.2.1
Requires-Dist: pydantic>=2.11.5
Requires-Dist: python-dotenv>=1.0.1
Requires-Dist: sentence-transformers>=4.1.0
Provides-Extra: all
Requires-Dist: sentence-transformers>=4.0.2; extra == 'all'
Provides-Extra: cli
Requires-Dist: click>=8.1.8; extra == 'cli'
Requires-Dist: rich>=14.0.0; extra == 'cli'
Requires-Dist: textual>=3.2.0; extra == 'cli'
Provides-Extra: memory
Requires-Dist: sentence-transformers>=4.0.2; extra == 'memory'
